{
  "suggest.echodocSupport": true,
  "suggest.maxCompleteItemCount": 20,
  "coc.preferences.formatOnSaveFiletypes": [
    "javascript",
    "typescript",
    "typescriptreact",
    "json",
    "javascriptreact",
    "typescript.tsx"
  ],
  "eslint.filetypes": [
    "javascript",
    "typescript",
    "typescriptreact",
    "javascriptreact",
    "typescript.tsx"
  ],
  "diagnostic.errorSign": "•",
  "diagnostic.warningSign": "•",
  "diagnostic.infoSign": "•",
  "languageserver": {
    "ccls": {
      "command": "ccls",
      "filetypes": ["c", "cc", "cpp", "c++", "objc", "objcpp"],
      "rootPatterns": ["compile_commands.json", ".git/", ".hg/"],
      "initializationOptions": {
        "cache": {
          "directory": "/tmp/ccls"
        }
      }
    }
  }
}
